Calculator/__init__.py
Calculator/calculator.py
CalculatorB-0.0.1.dist-info/LICENSE.txt
CalculatorB-0.0.1.dist-info/METADATA
CalculatorB-0.0.1.dist-info/WHEEL
CalculatorB-0.0.1.dist-info/top_level.txt
CalculatorB-0.0.1.dist-info/RECORD
