Metadata-Version: 2.1
Name: CalculatorB
Version: 0.0.1
Summary: Simple Calculator
Author: Kestutis Gricius
Author-email: gricius.k@gmail.com
Keywords: python,Calculator,CalculatorB
Classifier: Development Status :: 3 - Alpha
Classifier: Intended Audience :: Developers
Classifier: Programming Language :: Python :: 3
Classifier: Operating System :: MacOS :: MacOS X
Classifier: Operating System :: Microsoft :: Windows
License-File: LICENSE.txt
